hello_aaingyunii_pr-1.0.0.dist-info/METADATA
hello_aaingyunii_pr-1.0.0.dist-info/WHEEL
hello_aaingyunii_pr-1.0.0.dist-info/entry_points.txt
hello_aaingyunii_pr/.pytest_cache/.gitignore
hello_aaingyunii_pr/.pytest_cache/CACHEDIR.TAG
hello_aaingyunii_pr/.pytest_cache/README.md
hello_aaingyunii_pr/.pytest_cache/v/cache/nodeids
hello_aaingyunii_pr/.pytest_cache/v/cache/stepwise
hello_aaingyunii_pr/__init__.py
hello_aaingyunii_pr/my.py
hello_aaingyunii_pr/weather_show.py
hello_aaingyunii_pr/who.py
hello_aaingyunii_pr-1.0.0.dist-info/RECORD
