Metadata-Version: 2.1
Name: hello-aaingyunii_pr
Version: 1.0.0
Summary: The Python program I'm distributing for the first time
Author-Email: aaingyunii <dlsrbs98@gmail.com>
License: MIT
Project-URL: Homepage, https://github.com/aaingyunii/hello-aaingyunii_pr
Project-URL: Bug tracker, https://github.com/aaingyunii/hello-aaingyunii_pr/issues
Requires-Python: >=3.8
Requires-Dist: requests>=2.31.0
Requires-Dist: beautifulsoup4>=4.12.2
